pylint_report/__init__.py
pylint_report/_version.py
pylint_report/pylint_report.py
pylint_report/style/pylint-report.css
pylint_report/style/template.html.j2
pylint_report/utest/test_pylint_report.py
pylint_report/utest/resources/.pylint_report_utest.html
pylint_report/utest/resources/.pylint_report_utest.json
pylint_report/utest/resources/.pylint_report_utest_no_messages.json
pylint_report/utest/resources/__init__.py
pylint_report/utest/resources/linting_problems.py
pylint_report/utest/resources/more_problems.py
pylint_report/utest/resources/no_problems.py
pylint_report-2.4.2.dist-info/METADATA
pylint_report-2.4.2.dist-info/WHEEL
pylint_report-2.4.2.dist-info/entry_points.txt
pylint_report-2.4.2.dist-info/top_level.txt
pylint_report-2.4.2.dist-info/RECORD
