Metadata-Version: 2.2
Name: pylint_report
Version: 2.4.2
Summary: Generates an html report summarizing the results of pylint.
Author-email: Dimitar Dimitrov <mail.mitko@gmail.com>
License: Apache 2.0
Project-URL: homepage, https://github.com/drdv/pylint-report
Project-URL: documentation, https://drdv.github.io/pylint-report
Requires-Python: >=3.8
Requires-Dist: pylint
Requires-Dist: Jinja2
Requires-Dist: pandas
Requires-Dist: argcomplete
Provides-Extra: test
Requires-Dist: pytest; extra == "test"
Requires-Dist: coverage; extra == "test"
Requires-Dist: pytest-reportlog; extra == "test"
Requires-Dist: pytest-html; extra == "test"
Provides-Extra: docs
Requires-Dist: Sphinx; extra == "docs"
Requires-Dist: sphinx-rtd-theme; extra == "docs"
Requires-Dist: sphinxcontrib-jsmath; extra == "docs"
Requires-Dist: sphinxcontrib-websupport; extra == "docs"
Requires-Dist: sphinx-copybutton; extra == "docs"
Requires-Dist: sphinx-inline-tabs; extra == "docs"
Requires-Dist: sphinx-argparse; extra == "docs"
Requires-Dist: furo; extra == "docs"
Provides-Extra: code
Requires-Dist: black; extra == "code"
Requires-Dist: isort; extra == "code"
Requires-Dist: pre-commit; extra == "code"
Provides-Extra: dev
Requires-Dist: pylint_report[code,docs,test]; extra == "dev"
